xia_prompts_metagpt/__init__.py
xia_prompts_metagpt/prompts.cpython-311-darwin.so
xia_prompts_metagpt/templates/campaigns/software_initialization.json
xia_prompts_metagpt/templates/missions/architecture_design.json
xia_prompts_metagpt/templates/missions/product_design.json
xia_prompts_metagpt/templates/missions/project_management.json
xia_prompts_metagpt/templates/missions/python_development.json
xia_prompts_metagpt/templates/prompts/develop_python.prompt
xia_prompts_metagpt/templates/prompts/work.prompt
xia_prompts_metagpt/templates/skills/software/architect.bio
xia_prompts_metagpt/templates/skills/software/developer_python.bio
xia_prompts_metagpt/templates/skills/software/product_manager.bio
xia_prompts_metagpt/templates/skills/software/project_manager.bio
xia_prompts_metagpt/templates/tasks/design/data_structures_and_interface_definitions.prompt
xia_prompts_metagpt/templates/tasks/design/development_task_list.prompt
xia_prompts_metagpt/templates/tasks/design/implement_approach.prompt
xia_prompts_metagpt/templates/tasks/design/logic_analysis.prompt
xia_prompts_metagpt/templates/tasks/design/program_call_flow.prompt
xia_prompts_metagpt/templates/tasks/design/python_package_name.prompt
xia_prompts_metagpt/templates/tasks/design/required_python_third_party_packages.prompt
xia_prompts_metagpt/templates/tasks/design/shared_knowledge.prompt
xia_prompts_metagpt/templates/tasks/design/source_code_file_list.prompt
xia_prompts_metagpt/templates/tasks/develop/python_general.prompt
xia_prompts_metagpt/templates/tasks/requirements/product_goals.prompt
xia_prompts_metagpt/templates/tasks/requirements/requirement_analysis.prompt
xia_prompts_metagpt/templates/tasks/requirements/user_stories.prompt
xia_prompts_metagpt/templates/tasks/reviews/bug_detected.prompt
xia_prompts_metagpt/templates/tasks/reviews/potential_issue_detected
xia_prompts_metagpt/templates/tasks/reviews/review_passed.prompt
xia_prompts_metagpt-0.0.3.dist-info/LICENSE.txt
xia_prompts_metagpt-0.0.3.dist-info/METADATA
xia_prompts_metagpt-0.0.3.dist-info/WHEEL
xia_prompts_metagpt-0.0.3.dist-info/top_level.txt
xia_prompts_metagpt-0.0.3.dist-info/RECORD
