Metadata-Version: 2.1
Name: xia-prompts-metagpt
Version: 0.0.3
Home-page: https://develop.x-i-a.com/docs/xia-prompts-metagpt/0.0.3/index.html
Author: X-I-A
Author-email: admin@x-i-a.com
Requires-Python: >=3.9
License-File: LICENSE.txt
Requires-Dist: xia-composer
